{
  "required": true,
  "minVersion": "0.8",
  "package": "org.amateras_smp.amacarpet.mixins",
  "compatibilityLevel": "{{COMPATIBILITY_LEVEL}}",
  "mixins": [
    "network.MixinPlayerList",
    "sound.MixinLevel",
    "spawn.MixinFlatLevelSource",
    "spawn.MixinNoiseBasedChunkGenerator",
    "syncmatica.MixinServerCommunicationManager",
    "syncmatica.MixinSyncmaticManager",
    "ticket.MixinChunkMap",
    "ticket.MixinMinecraftServer",
    "ticket.MixinServerChunkCache",
    "ticket.MixinServerLevel",
    "ticket.MixinTheEndGatewayBlockEntity",
    "util.MixinMinecraftServer"
  ],
  "injectors": {
    "defaultRequire": 1
  }
}
